codelog/__init__.py
codelog/__main__.py
codelog/cli.py
codelog-0.1.0.dist-info/METADATA
codelog-0.1.0.dist-info/WHEEL
codelog-0.1.0.dist-info/entry_points.txt
codelog-0.1.0.dist-info/top_level.txt
codelog-0.1.0.dist-info/RECORD
